rfc9290/__init__.py
rfc9290/rfc9290.py
rfc9290/test.py
rfc9290-0.1.1.dist-info/LICENSE
rfc9290-0.1.1.dist-info/METADATA
rfc9290-0.1.1.dist-info/WHEEL
rfc9290-0.1.1.dist-info/top_level.txt
rfc9290-0.1.1.dist-info/RECORD
