Metadata-Version: 2.1
Name: rfc9290
Version: 0.1.1
Summary: Simple encoder/decoder for RFC 9290 Concise Problem Details
Home-page: https://github.com/JAG-UK/rfc9290
Author: JAG-UK
License: MIT
Classifier: Programming Language :: Python :: 3
Classifier: License :: OSI Approved :: MIT License
Classifier: Operating System :: OS Independent
Requires-Python: >=3.6
License-File: LICENSE
Requires-Dist: cbor2
